{
  "__CONTENT__" : "metadata",
  "__COMMON__" : {
    "SIMPLE" : true,
    "BITPIX" : 8,
    "NAXIS" : 0,
    "EXTEND" : true,
    "RUNNUM" : 14507,
    "MJD" : 60405.12110961473,
    "DATE" : "2024-04-05T02:54:23.871",
    "DAYOBS" : "20240405",
    "SEQNUM" : 267,
    "CONTRLLR" : "S",
    "EXPTIME" : 30.0,
    "DARKTIME" : 30.0,
    "TIMESYS" : "TAI",
    "LSST_NUM" : "ITL-3800C-283",
    "IMGTYPE" : "SKYEXP",
    "OBSTYPE" : "SKYEXP",
    "REASON" : "survey",
    "MONOWL" : -1,
    "ROTANGLE" : 149.9388578846546,
    "FILTER" : "i_06",
    "TELESCOP" : "Simonyi Survey Telescope",
    "INSTRUME" : "ComCamSim",
    "RAFTBAY" : "R22",
    "CCDSLOT" : "S11",
    "RA" : 224.984993554161,
    "DEC" : -39.80449322125821,
    "ROTCOORD" : "sky",
    "ROTPA" : 149.9388578846546,
    "OBSID" : "CC_S_20240405_000267",
    "HIERARCH SIMULATED MJD-OBS" : 60405.12093600362,
    "HASTART" : -58.29035829907704,
    "HAEND" : -58.165016064126576,
    "HIERARCH SIMULATED DATE-OBS" : "2024-04-05T02:54:08.871",
    "HIERARCH SIMULATED DATE-END" : "2024-04-05T02:54:38.871",
    "AMSTART" : 1.4899674619440912,
    "AMEND" : 1.4899674619440912,
    "IMSIMVER" : "2.0",
    "PKG00000" : "throughputs",
    "VER00000" : "1.4",
    "CHIPID" : "R22_S11",
    "FOCUSZ" : 0.0,
    "OUTFILE" : "amp_00014507-0-i-R22_S11-det004.fits.fz"
  },
  "amp_00014507-0-i-R22_S11-det004.fits.fz" : { }
}