{
  "__CONTENT__" : "metadata",
  "__COMMON__" : {
    "SIMPLE" : true,
    "BITPIX" : 8,
    "NAXIS" : 0,
    "EXTEND" : true,
    "RUNNUM" : 14768,
    "MJD" : 60405.24116434352,
    "DATE" : "2024-04-05T05:47:16.599",
    "DAYOBS" : "20240405",
    "SEQNUM" : 528,
    "CONTRLLR" : "S",
    "EXPTIME" : 30.0,
    "DARKTIME" : 30.0,
    "TIMESYS" : "TAI",
    "LSST_NUM" : "ITL-3800C-283",
    "IMGTYPE" : "SKYEXP",
    "OBSTYPE" : "SKYEXP",
    "REASON" : "survey",
    "MONOWL" : -1,
    "ROTANGLE" : 167.80890372331433,
    "FILTER" : "g_01",
    "TELESCOP" : "Simonyi Survey Telescope",
    "INSTRUME" : "ComCamSim",
    "RAFTBAY" : "R22",
    "CCDSLOT" : "S11",
    "RA" : 225.21200772544424,
    "DEC" : -39.9849517467574,
    "ROTCOORD" : "sky",
    "ROTPA" : 167.80890372331433,
    "OBSID" : "CC_S_20240405_000528",
    "HIERARCH SIMULATED MJD-OBS" : 60405.24099073241,
    "HASTART" : -15.179340028462576,
    "HAEND" : -15.053997794218901,
    "HIERARCH SIMULATED DATE-OBS" : "2024-04-05T05:47:01.599",
    "HIERARCH SIMULATED DATE-END" : "2024-04-05T05:47:31.599",
    "AMSTART" : 1.0390175694088268,
    "AMEND" : 1.0390175694088268,
    "IMSIMVER" : "2.0",
    "PKG00000" : "throughputs",
    "VER00000" : "1.4",
    "CHIPID" : "R22_S11",
    "FOCUSZ" : 0.0,
    "OUTFILE" : "amp_00014768-0-g-R22_S11-det004.fits.fz"
  },
  "amp_00014768-0-g-R22_S11-det004.fits.fz" : { }
}