{
  "__CONTENT__" : "metadata",
  "__COMMON__" : {
    "SIMPLE" : true,
    "BITPIX" : 8,
    "NAXIS" : 0,
    "EXTEND" : true,
    "RUNNUM" : 12460,
    "MJD" : 60403.067693516474,
    "DATE" : "2024-04-03T01:37:28.720",
    "DAYOBS" : "20240403",
    "SEQNUM" : 150,
    "CONTRLLR" : "S",
    "EXPTIME" : 30.0,
    "DARKTIME" : 30.0,
    "TIMESYS" : "TAI",
    "LSST_NUM" : "ITL-3800C-283",
    "IMGTYPE" : "SKYEXP",
    "OBSTYPE" : "SKYEXP",
    "REASON" : "survey",
    "MONOWL" : -1,
    "ROTANGLE" : 23.371892248962418,
    "FILTER" : "i_06",
    "TELESCOP" : "Simonyi Survey Telescope",
    "INSTRUME" : "ComCamSim",
    "RAFTBAY" : "R22",
    "CCDSLOT" : "S11",
    "RA" : 149.95567866010785,
    "DEC" : 2.28576518072453,
    "ROTCOORD" : "sky",
    "ROTPA" : 23.371892248962418,
    "OBSID" : "CC_S_20240403_000150",
    "HIERARCH SIMULATED MJD-OBS" : 60403.067519905366,
    "HASTART" : -4.514792216494499,
    "HAEND" : -4.389449971053068,
    "HIERARCH SIMULATED DATE-OBS" : "2024-04-03T01:37:13.720",
    "HIERARCH SIMULATED DATE-END" : "2024-04-03T01:37:43.720",
    "AMSTART" : 1.1898888057428405,
    "AMEND" : 1.1898888057428405,
    "IMSIMVER" : "2.0",
    "PKG00000" : "throughputs",
    "VER00000" : "1.4",
    "CHIPID" : "R22_S11",
    "FOCUSZ" : 0.0,
    "OUTFILE" : "amp_00012460-0-i-R22_S11-det004.fits.fz"
  },
  "amp_00012460-0-i-R22_S11-det004.fits.fz" : { }
}