{
  "__CONTENT__" : "metadata",
  "SIMPLE" : true,
  "BITPIX" : 8,
  "NAXIS" : 0,
  "EXTEND" : true,
  "RUNNUM" : 16021,
  "MJD" : 60489.35263433755,
  "DATE" : "2024-06-28T08:27:47.607",
  "DAYOBS" : "20240627",
  "SEQNUM" : 878,
  "CONTRLLR" : "S",
  "EXPTIME" : 30.0,
  "DARKTIME" : 30.0,
  "TIMESYS" : "TAI",
  "LSST_NUM" : "ITL-3800C-283",
  "IMGTYPE" : "SKYEXP",
  "OBSTYPE" : "SKYEXP",
  "REASON" : "survey",
  "MONOWL" : -1,
  "ROTANGLE" : 343.05854240394274,
  "FILTER" : "g_01",
  "INSTRUME" : "ComCamSim",
  "RAFTBAY" : "R22",
  "CCDSLOT" : "S11",
  "RA" : 279.99435559622805,
  "DEC" : -47.87122175776069,
  "ROTCOORD" : "sky",
  "ROTPA" : 343.05854240394274,
  "TELESCOP" : "Simonyi Survey Telescope",
  "TELCODE" : "CC",
  "RASTART" : 279.99435559622805,
  "DECSTART" : -47.87122175776069,
  "ELSTART" : 46.2057152234389,
  "AZSTART" : 230.7765037105571,
  "RADESYS" : "ICRS",
  "TRACKSYS" : "RADEC",
  "OBSID" : "CC_S_20240627_000878",
  "HIERARCH SIMULATED MJD-OBS" : 60489.35246072644,
  "HASTART" : 53.07217243511076,
  "HAEND" : 53.19751466801614,
  "HIERARCH SIMULATED DATE-OBS" : "2024-06-28T08:27:32.607",
  "HIERARCH SIMULATED DATE-END" : "2024-06-28T08:28:02.607",
  "AMSTART" : 1.385369155707989,
  "AMEND" : 1.385369155707989,
  "ORIGIN" : "imSim",
  "IMSIMVER" : "2.0",
  "PKG00000" : "throughputs",
  "VER00000" : "1.9",
  "CHIPID" : "R22_S11",
  "FOCUSZ" : 0.0,
  "OUTFILE" : "amp_00016021-0-g-R22_S11-det004.fits.fz"
}