{
  "__CONTENT__" : "metadata",
  "SIMPLE" : true,
  "BITPIX" : 8,
  "NAXIS" : 0,
  "EXTEND" : true,
  "RUNNUM" : 14941,
  "MJD" : 60488.35663036621,
  "DATE" : "2024-06-27T08:33:32.864",
  "DAYOBS" : "20240626",
  "SEQNUM" : 886,
  "CONTRLLR" : "S",
  "EXPTIME" : 30.0,
  "DARKTIME" : 30.0,
  "TIMESYS" : "TAI",
  "LSST_NUM" : "ITL-3800C-283",
  "IMGTYPE" : "SKYEXP",
  "OBSTYPE" : "SKYEXP",
  "REASON" : "survey",
  "MONOWL" : -1,
  "ROTANGLE" : 153.33278754068033,
  "FILTER" : "i_06",
  "INSTRUME" : "ComCamSim",
  "RAFTBAY" : "R22",
  "CCDSLOT" : "S11",
  "RA" : 9.482200583218944,
  "DEC" : -43.87817224049953,
  "ROTCOORD" : "sky",
  "ROTPA" : 153.33278754068033,
  "TELESCOP" : "Simonyi Survey Telescope",
  "TELCODE" : "CC",
  "RASTART" : 9.482200583218944,
  "DECSTART" : -43.87817224049953,
  "ELSTART" : 58.54781811421772,
  "AZSTART" : 125.76305325439033,
  "RADESYS" : "ICRS",
  "TRACKSYS" : "RADEC",
  "OBSID" : "CC_S_20240626_000886",
  "HIERARCH SIMULATED MJD-OBS" : 60488.3564567551,
  "HASTART" : 324.04120502055275,
  "HAEND" : 324.16654725516173,
  "HIERARCH SIMULATED DATE-OBS" : "2024-06-27T08:33:17.864",
  "HIERARCH SIMULATED DATE-END" : "2024-06-27T08:33:47.864",
  "AMSTART" : 1.1722285880208076,
  "AMEND" : 1.1722285880208076,
  "ORIGIN" : "imSim",
  "IMSIMVER" : "2.0",
  "PKG00000" : "throughputs",
  "VER00000" : "1.9",
  "CHIPID" : "R22_S11",
  "FOCUSZ" : 0.0,
  "OUTFILE" : "amp_00014941-0-i-R22_S11-det004.fits.fz"
}