{
  "__CONTENT__" : "metadata",
  "SIMPLE" : true,
  "BITPIX" : 8,
  "NAXIS" : 0,
  "EXTEND" : true,
  "RUNNUM" : 14604,
  "MJD" : 60488.199887115465,
  "DATE" : "2024-06-27T04:47:50.247",
  "DAYOBS" : "20240626",
  "SEQNUM" : 549,
  "CONTRLLR" : "S",
  "EXPTIME" : 30.0,
  "DARKTIME" : 30.0,
  "TIMESYS" : "TAI",
  "LSST_NUM" : "ITL-3800C-283",
  "IMGTYPE" : "SKYEXP",
  "OBSTYPE" : "SKYEXP",
  "REASON" : "survey",
  "MONOWL" : -1,
  "ROTANGLE" : 257.0692729840537,
  "FILTER" : "i_06",
  "INSTRUME" : "ComCamSim",
  "RAFTBAY" : "R22",
  "CCDSLOT" : "S11",
  "RA" : 279.97480626652134,
  "DEC" : -47.986124285981056,
  "ROTCOORD" : "sky",
  "ROTPA" : 257.0692729840537,
  "TELESCOP" : "Simonyi Survey Telescope",
  "TELCODE" : "CC",
  "RASTART" : 279.97480626652134,
  "DECSTART" : -47.986124285981056,
  "ELSTART" : 72.10520689911255,
  "AZSTART" : 173.3508416057778,
  "RADESYS" : "ICRS",
  "TRACKSYS" : "RADEC",
  "OBSID" : "CC_S_20240626_000549",
  "HIERARCH SIMULATED MJD-OBS" : 60488.19971350436,
  "HASTART" : -3.033462599567997,
  "HAEND" : -2.908120364442482,
  "HIERARCH SIMULATED DATE-OBS" : "2024-06-27T04:47:35.247",
  "HIERARCH SIMULATED DATE-END" : "2024-06-27T04:48:05.247",
  "AMSTART" : 1.0508370459836367,
  "AMEND" : 1.0508370459836367,
  "ORIGIN" : "imSim",
  "IMSIMVER" : "2.0",
  "PKG00000" : "throughputs",
  "VER00000" : "1.9",
  "CHIPID" : "R22_S11",
  "FOCUSZ" : 0.0,
  "OUTFILE" : "amp_00014604-0-i-R22_S11-det004.fits.fz"
}