{
  "__CONTENT__" : "metadata",
  "__COMMON__" : {
    "SIMPLE" : true,
    "BITPIX" : 8,
    "NAXIS" : 0,
    "EXTEND" : true,
    "RUNNUM" : 14388,
    "MJD" : 60405.06692231406,
    "DATE" : "2024-04-05T01:36:22.088",
    "DAYOBS" : "20240405",
    "SEQNUM" : 148,
    "CONTRLLR" : "S",
    "EXPTIME" : 30.0,
    "DARKTIME" : 30.0,
    "TIMESYS" : "TAI",
    "LSST_NUM" : "ITL-3800C-283",
    "IMGTYPE" : "SKYEXP",
    "OBSTYPE" : "SKYEXP",
    "REASON" : "survey",
    "MONOWL" : -1,
    "ROTANGLE" : 97.78383393887128,
    "FILTER" : "i_06",
    "TELESCOP" : "Simonyi Survey Telescope",
    "INSTRUME" : "ComCamSim",
    "RAFTBAY" : "R22",
    "CCDSLOT" : "S11",
    "RA" : 150.13653792603608,
    "DEC" : 1.9853914835891764,
    "ROTCOORD" : "sky",
    "ROTPA" : 97.78383393887128,
    "OBSID" : "CC_S_20240405_000148",
    "HIERARCH SIMULATED MJD-OBS" : 60405.06674870295,
    "HASTART" : -3.0027398645899837,
    "HAEND" : -2.877397629318722,
    "HIERARCH SIMULATED DATE-OBS" : "2024-04-05T01:36:07.088",
    "HIERARCH SIMULATED DATE-END" : "2024-04-05T01:36:37.088",
    "AMSTART" : 1.183824385024327,
    "AMEND" : 1.183824385024327,
    "IMSIMVER" : "2.0",
    "PKG00000" : "throughputs",
    "VER00000" : "1.4",
    "CHIPID" : "R22_S11",
    "FOCUSZ" : 0.0,
    "OUTFILE" : "amp_00014388-0-i-R22_S11-det004.fits.fz"
  },
  "amp_00014388-0-i-R22_S11-det004.fits.fz" : { }
}