{
  "__CONTENT__" : "metadata",
  "__COMMON__" : {
    "SIMPLE" : true,
    "BITPIX" : 8,
    "NAXIS" : 0,
    "EXTEND" : true,
    "RUNNUM" : 13874,
    "MJD" : 60404.27581711292,
    "DATE" : "2024-04-04T06:37:10.599",
    "DAYOBS" : "20240404",
    "SEQNUM" : 603,
    "CONTRLLR" : "S",
    "EXPTIME" : 30.0,
    "DARKTIME" : 30.0,
    "TIMESYS" : "TAI",
    "LSST_NUM" : "ITL-3800C-283",
    "IMGTYPE" : "SKYEXP",
    "OBSTYPE" : "SKYEXP",
    "REASON" : "survey",
    "MONOWL" : -1,
    "ROTANGLE" : 103.28578880228584,
    "FILTER" : "i_06",
    "TELESCOP" : "Simonyi Survey Telescope",
    "INSTRUME" : "ComCamSim",
    "RAFTBAY" : "R22",
    "CCDSLOT" : "S11",
    "RA" : 216.03062297592584,
    "DEC" : -12.577603896959898,
    "ROTCOORD" : "sky",
    "ROTPA" : 103.28578880228584,
    "OBSID" : "CC_S_20240404_000603",
    "HIERARCH SIMULATED MJD-OBS" : 60404.27564350181,
    "HASTART" : 5.52555527405346,
    "HAEND" : 5.650897513939697,
    "HIERARCH SIMULATED DATE-OBS" : "2024-04-04T06:36:55.599",
    "HIERARCH SIMULATED DATE-END" : "2024-04-04T06:37:25.599",
    "AMSTART" : 1.0538089035049811,
    "AMEND" : 1.0538089035049811,
    "IMSIMVER" : "2.0",
    "PKG00000" : "throughputs",
    "VER00000" : "1.4",
    "CHIPID" : "R22_S11",
    "FOCUSZ" : 0.0,
    "OUTFILE" : "amp_00013874-0-i-R22_S11-det004.fits.fz"
  },
  "amp_00013874-0-i-R22_S11-det004.fits.fz" : { }
}