{
  "__CONTENT__" : "metadata",
  "SIMPLE" : true,
  "BITPIX" : 8,
  "NAXIS" : 0,
  "EXTEND" : true,
  "RUNNUM" : 14291,
  "MJD" : 60488.05768005649,
  "DATE" : "2024-06-27T01:23:03.557",
  "DAYOBS" : "20240626",
  "SEQNUM" : 236,
  "CONTRLLR" : "S",
  "EXPTIME" : 30.0,
  "DARKTIME" : 30.0,
  "TIMESYS" : "TAI",
  "LSST_NUM" : "ITL-3800C-283",
  "IMGTYPE" : "SKYEXP",
  "OBSTYPE" : "SKYEXP",
  "REASON" : "survey",
  "MONOWL" : -1,
  "ROTANGLE" : 134.58621747627862,
  "FILTER" : "r_03",
  "INSTRUME" : "ComCamSim",
  "RAFTBAY" : "R22",
  "CCDSLOT" : "S11",
  "RA" : 249.88688853318075,
  "DEC" : 2.0607981532470223,
  "ROTCOORD" : "sky",
  "ROTPA" : 134.58621747627862,
  "TELESCOP" : "Simonyi Survey Telescope",
  "TELCODE" : "CC",
  "RASTART" : 249.88688853318075,
  "DECSTART" : 2.0607981532470223,
  "ELSTART" : 50.243301811033426,
  "AZSTART" : 40.00705899090679,
  "RADESYS" : "ICRS",
  "TRACKSYS" : "RADEC",
  "OBSID" : "CC_S_20240626_000236",
  "HIERARCH SIMULATED MJD-OBS" : 60488.05750644538,
  "HASTART" : -24.280250597703088,
  "HAEND" : -24.154908362056602,
  "HIERARCH SIMULATED DATE-OBS" : "2024-06-27T01:22:48.557",
  "HIERARCH SIMULATED DATE-END" : "2024-06-27T01:23:18.557",
  "AMSTART" : 1.3007841194455594,
  "AMEND" : 1.3007841194455594,
  "ORIGIN" : "imSim",
  "IMSIMVER" : "2.0",
  "PKG00000" : "throughputs",
  "VER00000" : "1.9",
  "CHIPID" : "R22_S11",
  "FOCUSZ" : 0.0,
  "OUTFILE" : "amp_00014291-0-r-R22_S11-det004.fits.fz"
}