{
  "__CONTENT__" : "metadata",
  "SIMPLE" : true,
  "BITPIX" : 8,
  "NAXIS" : 0,
  "EXTEND" : true,
  "RUNNUM" : 15353,
  "MJD" : 60489.046206383115,
  "DATE" : "2024-06-28T01:06:32.232",
  "DAYOBS" : "20240627",
  "SEQNUM" : 210,
  "CONTRLLR" : "S",
  "EXPTIME" : 30.0,
  "DARKTIME" : 30.0,
  "TIMESYS" : "TAI",
  "LSST_NUM" : "ITL-3800C-283",
  "IMGTYPE" : "SKYEXP",
  "OBSTYPE" : "SKYEXP",
  "REASON" : "survey",
  "MONOWL" : -1,
  "ROTANGLE" : 100.58007136877143,
  "FILTER" : "g_01",
  "INSTRUME" : "ComCamSim",
  "RAFTBAY" : "R22",
  "CCDSLOT" : "S11",
  "RA" : 249.92768091033054,
  "DEC" : 1.9542686734954409,
  "ROTCOORD" : "sky",
  "ROTPA" : 100.58007136877143,
  "TELESCOP" : "Simonyi Survey Telescope",
  "TELCODE" : "CC",
  "RASTART" : 249.92768091033054,
  "DECSTART" : 1.9542686734954409,
  "ELSTART" : 48.479690798700815,
  "AZSTART" : 44.10217860330103,
  "RADESYS" : "ICRS",
  "TRACKSYS" : "RADEC",
  "OBSID" : "CC_S_20240627_000210",
  "HIERARCH SIMULATED MJD-OBS" : 60489.04603277201,
  "HASTART" : -27.477241010067843,
  "HAEND" : -27.35189877694745,
  "HIERARCH SIMULATED DATE-OBS" : "2024-06-28T01:06:17.232",
  "HIERARCH SIMULATED DATE-END" : "2024-06-28T01:06:47.232",
  "AMSTART" : 1.3356113523587103,
  "AMEND" : 1.3356113523587103,
  "ORIGIN" : "imSim",
  "IMSIMVER" : "2.0",
  "PKG00000" : "throughputs",
  "VER00000" : "1.9",
  "CHIPID" : "R22_S11",
  "FOCUSZ" : 0.0,
  "OUTFILE" : "amp_00015353-0-g-R22_S11-det004.fits.fz"
}