{
  "__CONTENT__" : "metadata",
  "__COMMON__" : {
    "SIMPLE" : true,
    "BITPIX" : 8,
    "NAXIS" : 0,
    "EXTEND" : true,
    "RUNNUM" : 13547,
    "MJD" : 60404.12643974268,
    "DATE" : "2024-04-04T03:02:04.394",
    "DAYOBS" : "20240404",
    "SEQNUM" : 276,
    "CONTRLLR" : "S",
    "EXPTIME" : 30.0,
    "DARKTIME" : 30.0,
    "TIMESYS" : "TAI",
    "LSST_NUM" : "ITL-3800C-283",
    "IMGTYPE" : "SKYEXP",
    "OBSTYPE" : "SKYEXP",
    "REASON" : "survey",
    "MONOWL" : -1,
    "ROTANGLE" : 187.23511262006784,
    "FILTER" : "g_01",
    "TELESCOP" : "Simonyi Survey Telescope",
    "INSTRUME" : "ComCamSim",
    "RAFTBAY" : "R22",
    "CCDSLOT" : "S11",
    "RA" : 225.13886674071918,
    "DEC" : -39.840271356882106,
    "ROTCOORD" : "sky",
    "ROTPA" : 187.23511262006784,
    "OBSID" : "CC_S_20240404_000276",
    "HIERARCH SIMULATED MJD-OBS" : 60404.12626613157,
    "HASTART" : -57.50577571326804,
    "HAEND" : -57.38043347256422,
    "HIERARCH SIMULATED DATE-OBS" : "2024-04-04T03:01:49.394",
    "HIERARCH SIMULATED DATE-END" : "2024-04-04T03:02:19.394",
    "AMSTART" : 1.4729459799754403,
    "AMEND" : 1.4729459799754403,
    "IMSIMVER" : "2.0",
    "PKG00000" : "throughputs",
    "VER00000" : "1.4",
    "CHIPID" : "R22_S11",
    "FOCUSZ" : 0.0,
    "OUTFILE" : "amp_00013547-0-g-R22_S11-det004.fits.fz"
  },
  "amp_00013547-0-g-R22_S11-det004.fits.fz" : { }
}