{
  "__CONTENT__" : "metadata",
  "SIMPLE" : true,
  "BITPIX" : 8,
  "NAXIS" : 0,
  "EXTEND" : true,
  "RUNNUM" : 15208,
  "MJD" : 60488.98079363727,
  "DATE" : "2024-06-27T23:32:20.570",
  "DAYOBS" : "20240627",
  "SEQNUM" : 1153,
  "CONTRLLR" : "S",
  "EXPTIME" : 30.0,
  "DARKTIME" : 30.0,
  "TIMESYS" : "TAI",
  "LSST_NUM" : "ITL-3800C-283",
  "IMGTYPE" : "SKYEXP",
  "OBSTYPE" : "SKYEXP",
  "REASON" : "survey",
  "MONOWL" : -1,
  "ROTANGLE" : 146.6054480374329,
  "FILTER" : "i_06",
  "INSTRUME" : "ComCamSim",
  "RAFTBAY" : "R22",
  "CCDSLOT" : "S11",
  "RA" : 225.1767255801556,
  "DEC" : -39.990104236442946,
  "ROTCOORD" : "sky",
  "ROTPA" : 146.6054480374329,
  "TELESCOP" : "Simonyi Survey Telescope",
  "TELCODE" : "CC",
  "RASTART" : 225.1767255801556,
  "DECSTART" : -39.990104236442946,
  "ELSTART" : 66.46067455599136,
  "AZSTART" : 121.6186581337209,
  "RADESYS" : "ICRS",
  "TRACKSYS" : "RADEC",
  "OBSID" : "CC_S_20240627_001153",
  "HIERARCH SIMULATED MJD-OBS" : 60488.98062002616,
  "HASTART" : -26.339346971235784,
  "HAEND" : -26.21400473803149,
  "HIERARCH SIMULATED DATE-OBS" : "2024-06-27T23:32:05.570",
  "HIERARCH SIMULATED DATE-END" : "2024-06-27T23:32:35.570",
  "AMSTART" : 1.090766886327524,
  "AMEND" : 1.090766886327524,
  "ORIGIN" : "imSim",
  "IMSIMVER" : "2.0",
  "PKG00000" : "throughputs",
  "VER00000" : "1.9",
  "CHIPID" : "R22_S11",
  "FOCUSZ" : 0.0,
  "OUTFILE" : "amp_00015208-0-i-R22_S11-det004.fits.fz"
}