{
  "__CONTENT__" : "metadata",
  "SIMPLE" : true,
  "BITPIX" : 8,
  "NAXIS" : 0,
  "EXTEND" : true,
  "RUNNUM" : 15865,
  "MJD" : 60489.282413172514,
  "DATE" : "2024-06-28T06:46:40.498",
  "DAYOBS" : "20240627",
  "SEQNUM" : 722,
  "CONTRLLR" : "S",
  "EXPTIME" : 30.0,
  "DARKTIME" : 30.0,
  "TIMESYS" : "TAI",
  "LSST_NUM" : "ITL-3800C-283",
  "IMGTYPE" : "SKYEXP",
  "OBSTYPE" : "SKYEXP",
  "REASON" : "survey",
  "MONOWL" : -1,
  "ROTANGLE" : 69.67924994933594,
  "FILTER" : "r_03",
  "INSTRUME" : "ComCamSim",
  "RAFTBAY" : "R22",
  "CCDSLOT" : "S11",
  "RA" : 310.1657737238192,
  "DEC" : -19.07677458528497,
  "ROTCOORD" : "sky",
  "ROTPA" : 69.67924994933594,
  "TELESCOP" : "Simonyi Survey Telescope",
  "TELCODE" : "CC",
  "RASTART" : 310.1657737238192,
  "DECSTART" : -19.07677458528497,
  "ELSTART" : 78.61145547070518,
  "AZSTART" : 11.868053864789935,
  "RADESYS" : "ICRS",
  "TRACKSYS" : "RADEC",
  "OBSID" : "CC_S_20240627_000722",
  "HIERARCH SIMULATED MJD-OBS" : 60489.282239561406,
  "HASTART" : -2.4480771657397895,
  "HAEND" : -2.3227349328100786,
  "HIERARCH SIMULATED DATE-OBS" : "2024-06-28T06:46:25.498",
  "HIERARCH SIMULATED DATE-END" : "2024-06-28T06:46:55.498",
  "AMSTART" : 1.020084782041979,
  "AMEND" : 1.020084782041979,
  "ORIGIN" : "imSim",
  "IMSIMVER" : "2.0",
  "PKG00000" : "throughputs",
  "VER00000" : "1.9",
  "CHIPID" : "R22_S11",
  "FOCUSZ" : 0.0,
  "OUTFILE" : "amp_00015865-0-r-R22_S11-det004.fits.fz"
}