{
  "__CONTENT__" : "metadata",
  "SIMPLE" : true,
  "BITPIX" : 8,
  "NAXIS" : 0,
  "EXTEND" : true,
  "RUNNUM" : 13964,
  "MJD" : 60487.40521129911,
  "DATE" : "2024-06-26T09:43:30.256",
  "DAYOBS" : "20240625",
  "SEQNUM" : 990,
  "CONTRLLR" : "S",
  "EXPTIME" : 30.0,
  "DARKTIME" : 30.0,
  "TIMESYS" : "TAI",
  "LSST_NUM" : "ITL-3800C-283",
  "IMGTYPE" : "SKYEXP",
  "OBSTYPE" : "SKYEXP",
  "REASON" : "survey",
  "MONOWL" : -1,
  "ROTANGLE" : 197.24623827055237,
  "FILTER" : "g_01",
  "INSTRUME" : "ComCamSim",
  "RAFTBAY" : "R22",
  "CCDSLOT" : "S11",
  "RA" : 9.612399423424034,
  "DEC" : -44.01730821643072,
  "ROTCOORD" : "sky",
  "ROTPA" : 197.24623827055237,
  "TELESCOP" : "Simonyi Survey Telescope",
  "TELCODE" : "CC",
  "RASTART" : 9.612399423424034,
  "DECSTART" : -44.01730821643072,
  "ELSTART" : 69.29763875443031,
  "AZSTART" : 137.09856382194772,
  "RADESYS" : "ICRS",
  "TRACKSYS" : "RADEC",
  "OBSID" : "CC_S_20240625_000990",
  "HIERARCH SIMULATED MJD-OBS" : 60487.405037688004,
  "HASTART" : 340.4623855457959,
  "HAEND" : 340.58772778439527,
  "HIERARCH SIMULATED DATE-OBS" : "2024-06-26T09:43:15.256",
  "HIERARCH SIMULATED DATE-END" : "2024-06-26T09:43:45.256",
  "AMSTART" : 1.0690276923744846,
  "AMEND" : 1.0690276923744846,
  "ORIGIN" : "imSim",
  "IMSIMVER" : "2.0",
  "PKG00000" : "throughputs",
  "VER00000" : "1.9",
  "CHIPID" : "R22_S11",
  "FOCUSZ" : 0.0,
  "OUTFILE" : "amp_00013964-0-g-R22_S11-det004.fits.fz"
}