{
  "__CONTENT__" : "metadata",
  "SIMPLE" : true,
  "BITPIX" : 8,
  "NAXIS" : 0,
  "EXTEND" : true,
  "RUNNUM" : 15758,
  "MJD" : 60489.23193884714,
  "DATE" : "2024-06-28T05:33:59.516",
  "DAYOBS" : "20240627",
  "SEQNUM" : 615,
  "CONTRLLR" : "S",
  "EXPTIME" : 30.0,
  "DARKTIME" : 30.0,
  "TIMESYS" : "TAI",
  "LSST_NUM" : "ITL-3800C-283",
  "IMGTYPE" : "SKYEXP",
  "OBSTYPE" : "SKYEXP",
  "REASON" : "survey",
  "MONOWL" : -1,
  "ROTANGLE" : 361.0312057982695,
  "FILTER" : "r_03",
  "INSTRUME" : "ComCamSim",
  "RAFTBAY" : "R22",
  "CCDSLOT" : "S11",
  "RA" : 250.0663468910558,
  "DEC" : 1.9159594530742008,
  "ROTCOORD" : "sky",
  "ROTPA" : 361.0312057982695,
  "TELESCOP" : "Simonyi Survey Telescope",
  "TELCODE" : "CC",
  "RASTART" : 250.0663468910558,
  "DECSTART" : 1.9159594530742008,
  "ELSTART" : 40.553777319268015,
  "AZSTART" : 303.3572076334149,
  "RADESYS" : "ICRS",
  "TRACKSYS" : "RADEC",
  "OBSID" : "CC_S_20240627_000615",
  "HIERARCH SIMULATED MJD-OBS" : 60489.23176523603,
  "HASTART" : 39.43084353709554,
  "HAEND" : 39.55618577005362,
  "HIERARCH SIMULATED DATE-OBS" : "2024-06-28T05:33:44.516",
  "HIERARCH SIMULATED DATE-END" : "2024-06-28T05:34:14.516",
  "AMSTART" : 1.5380794497813572,
  "AMEND" : 1.5380794497813572,
  "ORIGIN" : "imSim",
  "IMSIMVER" : "2.0",
  "PKG00000" : "throughputs",
  "VER00000" : "1.9",
  "CHIPID" : "R22_S11",
  "FOCUSZ" : 0.0,
  "OUTFILE" : "amp_00015758-0-r-R22_S11-det004.fits.fz"
}