{
  "__CONTENT__" : "metadata",
  "SIMPLE" : true,
  "BITPIX" : 8,
  "NAXIS" : 0,
  "EXTEND" : true,
  "RUNNUM" : 13895,
  "MJD" : 60487.373888109534,
  "DATE" : "2024-06-26T08:58:23.933",
  "DAYOBS" : "20240625",
  "SEQNUM" : 921,
  "CONTRLLR" : "S",
  "EXPTIME" : 30.0,
  "DARKTIME" : 30.0,
  "TIMESYS" : "TAI",
  "LSST_NUM" : "ITL-3800C-283",
  "IMGTYPE" : "SKYEXP",
  "OBSTYPE" : "SKYEXP",
  "REASON" : "survey",
  "MONOWL" : -1,
  "ROTANGLE" : 348.0614974032113,
  "FILTER" : "g_01",
  "INSTRUME" : "ComCamSim",
  "RAFTBAY" : "R22",
  "CCDSLOT" : "S11",
  "RA" : 280.20752603434426,
  "DEC" : -47.91295636507081,
  "ROTCOORD" : "sky",
  "ROTPA" : 348.0614974032113,
  "TELESCOP" : "Simonyi Survey Telescope",
  "TELCODE" : "CC",
  "RASTART" : 280.20752603434426,
  "DECSTART" : -47.91295636507081,
  "ELSTART" : 42.52776975797794,
  "AZSTART" : 230.88300835545414,
  "RADESYS" : "ICRS",
  "TRACKSYS" : "RADEC",
  "OBSID" : "CC_S_20240625_000921",
  "HIERARCH SIMULATED MJD-OBS" : 60487.373714498426,
  "HASTART" : 58.56003710347579,
  "HAEND" : 58.68537934223599,
  "HIERARCH SIMULATED DATE-OBS" : "2024-06-26T08:58:08.933",
  "HIERARCH SIMULATED DATE-END" : "2024-06-26T08:58:38.933",
  "AMSTART" : 1.4794049072390538,
  "AMEND" : 1.4794049072390538,
  "ORIGIN" : "imSim",
  "IMSIMVER" : "2.0",
  "PKG00000" : "throughputs",
  "VER00000" : "1.9",
  "CHIPID" : "R22_S11",
  "FOCUSZ" : 0.0,
  "OUTFILE" : "amp_00013895-0-g-R22_S11-det004.fits.fz"
}