{
  "__CONTENT__" : "metadata",
  "SIMPLE" : true,
  "BITPIX" : 8,
  "NAXIS" : 0,
  "EXTEND" : true,
  "RUNNUM" : 15236,
  "MJD" : 60488.99330729295,
  "DATE" : "2024-06-27T23:50:21.750",
  "DAYOBS" : "20240627",
  "SEQNUM" : 1181,
  "CONTRLLR" : "S",
  "EXPTIME" : 30.0,
  "DARKTIME" : 30.0,
  "TIMESYS" : "TAI",
  "LSST_NUM" : "ITL-3800C-283",
  "IMGTYPE" : "SKYEXP",
  "OBSTYPE" : "SKYEXP",
  "REASON" : "survey",
  "MONOWL" : -1,
  "ROTANGLE" : 191.4236082281688,
  "FILTER" : "g_01",
  "INSTRUME" : "ComCamSim",
  "RAFTBAY" : "R22",
  "CCDSLOT" : "S11",
  "RA" : 224.8308004829543,
  "DEC" : -40.08818221487014,
  "ROTCOORD" : "sky",
  "ROTPA" : 191.4236082281688,
  "TELESCOP" : "Simonyi Survey Telescope",
  "TELCODE" : "CC",
  "RASTART" : 224.8308004829543,
  "DECSTART" : -40.08818221487014,
  "ELSTART" : 69.93992436874011,
  "AZSTART" : 125.20631729767327,
  "RADESYS" : "ICRS",
  "TRACKSYS" : "RADEC",
  "OBSID" : "CC_S_20240627_001181",
  "HIERARCH SIMULATED MJD-OBS" : 60488.99313368184,
  "HASTART" : -21.47617198883185,
  "HAEND" : -21.35082975564592,
  "HIERARCH SIMULATED DATE-OBS" : "2024-06-27T23:50:06.750",
  "HIERARCH SIMULATED DATE-END" : "2024-06-27T23:50:36.750",
  "AMSTART" : 1.0645846341630352,
  "AMEND" : 1.0645846341630352,
  "ORIGIN" : "imSim",
  "IMSIMVER" : "2.0",
  "PKG00000" : "throughputs",
  "VER00000" : "1.9",
  "CHIPID" : "R22_S11",
  "FOCUSZ" : 0.0,
  "OUTFILE" : "amp_00015236-0-g-R22_S11-det004.fits.fz"
}