{
  "__CONTENT__" : "metadata",
  "__COMMON__" : {
    "SIMPLE" : true,
    "BITPIX" : 8,
    "NAXIS" : 0,
    "EXTEND" : true,
    "RUNNUM" : 14455,
    "MJD" : 60405.097998777404,
    "DATE" : "2024-04-05T02:21:07.094",
    "DAYOBS" : "20240405",
    "SEQNUM" : 215,
    "CONTRLLR" : "S",
    "EXPTIME" : 30.0,
    "DARKTIME" : 30.0,
    "TIMESYS" : "TAI",
    "LSST_NUM" : "ITL-3800C-283",
    "IMGTYPE" : "SKYEXP",
    "OBSTYPE" : "SKYEXP",
    "REASON" : "survey",
    "MONOWL" : -1,
    "ROTANGLE" : 117.44576851087574,
    "FILTER" : "g_01",
    "TELESCOP" : "Simonyi Survey Telescope",
    "INSTRUME" : "ComCamSim",
    "RAFTBAY" : "R22",
    "CCDSLOT" : "S11",
    "RA" : 179.6619005346102,
    "DEC" : -3.4126090251707E-4,
    "ROTCOORD" : "sky",
    "ROTPA" : 117.44576851087574,
    "OBSID" : "CC_S_20240405_000215",
    "HIERARCH SIMULATED MJD-OBS" : 60405.0978251663,
    "HASTART" : -21.309945582877532,
    "HAEND" : -21.184603347790357,
    "HIERARCH SIMULATED DATE-OBS" : "2024-04-05T02:20:52.094",
    "HIERARCH SIMULATED DATE-END" : "2024-04-05T02:21:22.094",
    "AMSTART" : 1.2426201341726641,
    "AMEND" : 1.2426201341726641,
    "IMSIMVER" : "2.0",
    "PKG00000" : "throughputs",
    "VER00000" : "1.4",
    "CHIPID" : "R22_S11",
    "FOCUSZ" : 0.0,
    "OUTFILE" : "amp_00014455-0-g-R22_S11-det004.fits.fz"
  },
  "amp_00014455-0-g-R22_S11-det004.fits.fz" : { }
}