{
  "__CONTENT__" : "metadata",
  "SIMPLE" : true,
  "BITPIX" : 8,
  "NAXIS" : 0,
  "EXTEND" : true,
  "RUNNUM" : 14090,
  "MJD" : 60487.966739780204,
  "DATE" : "2024-06-26T23:12:06.317",
  "DAYOBS" : "20240626",
  "SEQNUM" : 1116,
  "CONTRLLR" : "S",
  "EXPTIME" : 30.0,
  "DARKTIME" : 30.0,
  "TIMESYS" : "TAI",
  "LSST_NUM" : "ITL-3800C-283",
  "IMGTYPE" : "SKYEXP",
  "OBSTYPE" : "SKYEXP",
  "REASON" : "survey",
  "MONOWL" : -1,
  "ROTANGLE" : 125.34058408702882,
  "FILTER" : "g_01",
  "INSTRUME" : "ComCamSim",
  "RAFTBAY" : "R22",
  "CCDSLOT" : "S11",
  "RA" : 215.9936977425921,
  "DEC" : -12.615352478057497,
  "ROTCOORD" : "sky",
  "ROTPA" : 125.34058408702882,
  "TELESCOP" : "Simonyi Survey Telescope",
  "TELCODE" : "CC",
  "RASTART" : 215.9936977425921,
  "DECSTART" : -12.615352478057497,
  "ELSTART" : 62.214497942534805,
  "AZSTART" : 55.653350269534236,
  "RADESYS" : "ICRS",
  "TRACKSYS" : "RADEC",
  "OBSID" : "CC_S_20240626_001116",
  "HIERARCH SIMULATED MJD-OBS" : 60487.966566169096,
  "HASTART" : -23.215193461873525,
  "HAEND" : -23.08985122586651,
  "HIERARCH SIMULATED DATE-OBS" : "2024-06-26T23:11:51.317",
  "HIERARCH SIMULATED DATE-END" : "2024-06-26T23:12:21.317",
  "AMSTART" : 1.1303279932882282,
  "AMEND" : 1.1303279932882282,
  "ORIGIN" : "imSim",
  "IMSIMVER" : "2.0",
  "PKG00000" : "throughputs",
  "VER00000" : "1.9",
  "CHIPID" : "R22_S11",
  "FOCUSZ" : 0.0,
  "OUTFILE" : "amp_00014090-0-g-R22_S11-det004.fits.fz"
}