{
  "__CONTENT__" : "metadata",
  "__COMMON__" : {
    "SIMPLE" : true,
    "BITPIX" : 8,
    "NAXIS" : 0,
    "EXTEND" : true,
    "RUNNUM" : 13412,
    "MJD" : 60404.06451314784,
    "DATE" : "2024-04-04T01:32:53.936",
    "DAYOBS" : "20240404",
    "SEQNUM" : 141,
    "CONTRLLR" : "S",
    "EXPTIME" : 30.0,
    "DARKTIME" : 30.0,
    "TIMESYS" : "TAI",
    "LSST_NUM" : "ITL-3800C-283",
    "IMGTYPE" : "SKYEXP",
    "OBSTYPE" : "SKYEXP",
    "REASON" : "survey",
    "MONOWL" : -1,
    "ROTANGLE" : 66.4758720949628,
    "FILTER" : "i_06",
    "TELESCOP" : "Simonyi Survey Telescope",
    "INSTRUME" : "ComCamSim",
    "RAFTBAY" : "R22",
    "CCDSLOT" : "S11",
    "RA" : 149.97117007660734,
    "DEC" : 2.20915583533828,
    "ROTCOORD" : "sky",
    "ROTPA" : 66.4758720949628,
    "OBSID" : "CC_S_20240404_000141",
    "HIERARCH SIMULATED MJD-OBS" : 60404.06433953673,
    "HASTART" : -4.692691296668812,
    "HAEND" : -4.567349055634395,
    "HIERARCH SIMULATED DATE-OBS" : "2024-04-04T01:32:38.936",
    "HIERARCH SIMULATED DATE-END" : "2024-04-04T01:33:08.936",
    "AMSTART" : 1.1891790361209902,
    "AMEND" : 1.1891790361209902,
    "IMSIMVER" : "2.0",
    "PKG00000" : "throughputs",
    "VER00000" : "1.4",
    "CHIPID" : "R22_S11",
    "FOCUSZ" : 0.0,
    "OUTFILE" : "amp_00013412-0-i-R22_S11-det004.fits.fz"
  },
  "amp_00013412-0-i-R22_S11-det004.fits.fz" : { }
}