{
  "__CONTENT__" : "metadata",
  "SIMPLE" : true,
  "BITPIX" : 8,
  "NAXIS" : 0,
  "EXTEND" : true,
  "RUNNUM" : 13618,
  "MJD" : 60487.24594390684,
  "DATE" : "2024-06-26T05:54:09.554",
  "DAYOBS" : "20240625",
  "SEQNUM" : 644,
  "CONTRLLR" : "S",
  "EXPTIME" : 30.0,
  "DARKTIME" : 30.0,
  "TIMESYS" : "TAI",
  "LSST_NUM" : "ITL-3800C-283",
  "IMGTYPE" : "SKYEXP",
  "OBSTYPE" : "SKYEXP",
  "REASON" : "survey",
  "MONOWL" : -1,
  "ROTANGLE" : 170.94563336771262,
  "FILTER" : "i_06",
  "INSTRUME" : "ComCamSim",
  "RAFTBAY" : "R22",
  "CCDSLOT" : "S11",
  "RA" : 310.04982883016305,
  "DEC" : -18.972060371994015,
  "ROTCOORD" : "sky",
  "ROTPA" : 170.94563336771262,
  "TELESCOP" : "Simonyi Survey Telescope",
  "TELCODE" : "CC",
  "RASTART" : 310.04982883016305,
  "DECSTART" : -18.972060371994015,
  "ELSTART" : 70.5574077288525,
  "AZSTART" : 58.59039650442053,
  "RADESYS" : "ICRS",
  "TRACKSYS" : "RADEC",
  "OBSID" : "CC_S_20240625_000644",
  "HIERARCH SIMULATED MJD-OBS" : 60487.24577029573,
  "HASTART" : -17.46828653412581,
  "HAEND" : -17.342944294695883,
  "HIERARCH SIMULATED DATE-OBS" : "2024-06-26T05:53:54.554",
  "HIERARCH SIMULATED DATE-END" : "2024-06-26T05:54:24.554",
  "AMSTART" : 1.0604729650374003,
  "AMEND" : 1.0604729650374003,
  "ORIGIN" : "imSim",
  "IMSIMVER" : "2.0",
  "PKG00000" : "throughputs",
  "VER00000" : "1.9",
  "CHIPID" : "R22_S11",
  "FOCUSZ" : 0.0,
  "OUTFILE" : "amp_00013618-0-i-R22_S11-det004.fits.fz"
}