{
  "__CONTENT__" : "metadata",
  "SIMPLE" : true,
  "BITPIX" : 8,
  "NAXIS" : 0,
  "EXTEND" : true,
  "RUNNUM" : 16018,
  "MJD" : 60489.3514416855,
  "DATE" : "2024-06-28T08:26:04.562",
  "DAYOBS" : "20240627",
  "SEQNUM" : 875,
  "CONTRLLR" : "S",
  "EXPTIME" : 30.0,
  "DARKTIME" : 30.0,
  "TIMESYS" : "TAI",
  "LSST_NUM" : "ITL-3800C-283",
  "IMGTYPE" : "SKYEXP",
  "OBSTYPE" : "SKYEXP",
  "REASON" : "survey",
  "MONOWL" : -1,
  "ROTANGLE" : 345.5017266971328,
  "FILTER" : "g_01",
  "INSTRUME" : "ComCamSim",
  "RAFTBAY" : "R22",
  "CCDSLOT" : "S11",
  "RA" : 280.09085399194487,
  "DEC" : -47.99886933121632,
  "ROTCOORD" : "sky",
  "ROTPA" : 345.5017266971328,
  "TELESCOP" : "Simonyi Survey Telescope",
  "TELCODE" : "CC",
  "RASTART" : 280.09085399194487,
  "DECSTART" : -47.99886933121632,
  "ELSTART" : 46.54794596188703,
  "AZSTART" : 230.55469895089206,
  "RADESYS" : "ICRS",
  "TRACKSYS" : "RADEC",
  "OBSID" : "CC_S_20240627_000875",
  "HIERARCH SIMULATED MJD-OBS" : 60489.351268074395,
  "HASTART" : 52.54514378983254,
  "HAEND" : 52.670486022741386,
  "HIERARCH SIMULATED DATE-OBS" : "2024-06-28T08:25:49.562",
  "HIERARCH SIMULATED DATE-END" : "2024-06-28T08:26:19.562",
  "AMSTART" : 1.3775050677513596,
  "AMEND" : 1.3775050677513596,
  "ORIGIN" : "imSim",
  "IMSIMVER" : "2.0",
  "PKG00000" : "throughputs",
  "VER00000" : "1.9",
  "CHIPID" : "R22_S11",
  "FOCUSZ" : 0.0,
  "OUTFILE" : "amp_00016018-0-g-R22_S11-det004.fits.fz"
}