{
  "__CONTENT__" : "metadata",
  "__COMMON__" : {
    "SIMPLE" : true,
    "BITPIX" : 8,
    "NAXIS" : 0,
    "EXTEND" : true,
    "RUNNUM" : 13609,
    "MJD" : 60404.15502744597,
    "DATE" : "2024-04-04T03:43:14.371",
    "DAYOBS" : "20240404",
    "SEQNUM" : 338,
    "CONTRLLR" : "S",
    "EXPTIME" : 30.0,
    "DARKTIME" : 30.0,
    "TIMESYS" : "TAI",
    "LSST_NUM" : "ITL-3800C-283",
    "IMGTYPE" : "SKYEXP",
    "OBSTYPE" : "SKYEXP",
    "REASON" : "survey",
    "MONOWL" : -1,
    "ROTANGLE" : 99.46692882366281,
    "FILTER" : "g_01",
    "TELESCOP" : "Simonyi Survey Telescope",
    "INSTRUME" : "ComCamSim",
    "RAFTBAY" : "R22",
    "CCDSLOT" : "S11",
    "RA" : 179.6024112227782,
    "DEC" : -0.00789585300176467,
    "ROTCOORD" : "sky",
    "ROTPA" : 99.46692882366281,
    "OBSID" : "CC_S_20240404_000338",
    "HIERARCH SIMULATED MJD-OBS" : 60404.154853834865,
    "HASTART" : -1.6495694871443902,
    "HAEND" : -1.5242272465949327,
    "HIERARCH SIMULATED DATE-OBS" : "2024-04-04T03:42:59.371",
    "HIERARCH SIMULATED DATE-END" : "2024-04-04T03:43:29.371",
    "AMSTART" : 1.157956165358235,
    "AMEND" : 1.157956165358235,
    "IMSIMVER" : "2.0",
    "PKG00000" : "throughputs",
    "VER00000" : "1.4",
    "CHIPID" : "R22_S11",
    "FOCUSZ" : 0.0,
    "OUTFILE" : "amp_00013609-0-g-R22_S11-det004.fits.fz"
  },
  "amp_00013609-0-g-R22_S11-det004.fits.fz" : { }
}