{
  "__CONTENT__" : "metadata",
  "SIMPLE" : true,
  "BITPIX" : 8,
  "NAXIS" : 0,
  "EXTEND" : true,
  "RUNNUM" : 14532,
  "MJD" : 60488.166136280066,
  "DATE" : "2024-06-27T03:59:14.175",
  "DAYOBS" : "20240626",
  "SEQNUM" : 477,
  "CONTRLLR" : "S",
  "EXPTIME" : 30.0,
  "DARKTIME" : 30.0,
  "TIMESYS" : "TAI",
  "LSST_NUM" : "ITL-3800C-283",
  "IMGTYPE" : "SKYEXP",
  "OBSTYPE" : "SKYEXP",
  "REASON" : "survey",
  "MONOWL" : -1,
  "ROTANGLE" : 106.99616911603978,
  "FILTER" : "r_03",
  "INSTRUME" : "ComCamSim",
  "RAFTBAY" : "R22",
  "CCDSLOT" : "S11",
  "RA" : 309.92371382066625,
  "DEC" : -18.942642011813415,
  "ROTCOORD" : "sky",
  "ROTPA" : 106.99616911603978,
  "TELESCOP" : "Simonyi Survey Telescope",
  "TELCODE" : "CC",
  "RASTART" : 309.92371382066625,
  "DECSTART" : -18.942642011813415,
  "ELSTART" : 47.68627577618047,
  "AZSTART" : 85.28123974483145,
  "RADESYS" : "ICRS",
  "TRACKSYS" : "RADEC",
  "OBSID" : "CC_S_20240626_000477",
  "HIERARCH SIMULATED MJD-OBS" : 60488.16596266896,
  "HASTART" : -45.16593694093871,
  "HAEND" : -45.04059470569524,
  "HIERARCH SIMULATED DATE-OBS" : "2024-06-27T03:58:59.175",
  "HIERARCH SIMULATED DATE-END" : "2024-06-27T03:59:29.175",
  "AMSTART" : 1.3523201514478045,
  "AMEND" : 1.3523201514478045,
  "ORIGIN" : "imSim",
  "IMSIMVER" : "2.0",
  "PKG00000" : "throughputs",
  "VER00000" : "1.9",
  "CHIPID" : "R22_S11",
  "FOCUSZ" : 0.0,
  "OUTFILE" : "amp_00014532-0-r-R22_S11-det004.fits.fz"
}