{
  "__CONTENT__" : "metadata",
  "__COMMON__" : {
    "SIMPLE" : true,
    "BITPIX" : 8,
    "NAXIS" : 0,
    "EXTEND" : true,
    "DATE" : "2023-05-23T23:30:07.730",
    "MJD" : 60087.97925613448,
    "RUNNUM" : "7222D",
    "CCD_MANU" : "ITL",
    "CCD_TYPE" : "3800C",
    "TESTTYPE" : "FLAT",
    "IMGTYPE" : "FLAT",
    "DETSIZE" : "[1:4072,1:4000]",
    "EXPTIME" : 15.0,
    "FILENAME" : "TS_C_20230523_000295_R22_S11.fits",
    "BINX" : 1,
    "BINY" : 1,
    "CCDGAIN" : 1.0,
    "CCDNOISE" : 10.0,
    "HIERARCH SIMULATED DATE-OBS" : "2023-05-23T23:29:52.569",
    "HIERARCH SIMULATED MJD-OBS" : 60087.9790806598,
    "DATE-TRG" : "2023-05-23T23:30:07.722",
    "MJD-TRG" : 60087.979256041814,
    "IMAGETAG" : "e017f6892923953f",
    "CCDSLOT" : "S11",
    "RAFTBAY" : "R22",
    "FIRMWARE" : "3139500e",
    "PLATFORM" : "ir2-teststand",
    "CONTNUM" : "18ed9a7b",
    "DAQVERS" : "R5-V6.2 2023-05-17T21:16:12Z (39e4a179)",
    "DAQPART" : "ts8",
    "DAQFOLD" : "raw",
    "OBSANNOT" : "",
    "OBSID" : "TS_C_20230523_000295",
    "CAMCODE" : "TS",
    "CONTRLLR" : "C",
    "DAYOBS" : "20230523",
    "SEQNUM" : 295,
    "HEADVER" : 2,
    "INSTRUME" : "LSST-TS8",
    "TELESCOP" : "LSST",
    "TSTAND" : "TS8",
    "SEQFILE" : "FP_ITL_2s_ir2_v26.seq",
    "SEQCKSUM" : "1606982964",
    "LSST_NUM" : "ITL-3800C-062",
    "CCD_SERN" : "20804",
    "REBNAME" : "LCA-13574-093",
    "RAFTNAME" : "LCA-11021_RTM-004",
    "DARKTIME" : 15.153,
    "TSEQNUM" : 44,
    "FPVERS" : "1.1.8-dev-SNAPSHOT",
    "IHVERS" : "1.1.0-dev-SNAPSHOT",
    "DATE-BEG" : "2023-05-23T23:29:52.569",
    "MJD-BEG" : 60087.9790806598,
    "HIERARCH SIMULATED DATE-END" : "2023-05-23T23:30:07.722",
    "MJD-END" : 60087.979256041814,
    "TIMESYS" : "TAI",
    "FILTER" : null,
    "FILTER1" : null,
    "TEMPLED1" : 25.5272,
    "TEMPLED2" : 25.3017,
    "TEMPBRD" : 33.2544,
    "CCOBLED" : "red",
    "CCOBCURR" : 0.01,
    "CCOBADC" : 0.00843763,
    "CCOBFLST" : 0.114737,
    "PROJTIME" : 0.256,
    "CCOBFLUX" : 368.0,
    "DATEPBEG" : "2023-05-23T23:29:52.641",
    "MJDPBEG" : 60087.97908149287,
    "DATEPEND" : "2023-05-23T23:29:52.897",
    "MJDPEND" : 60087.979084455874,
    "CHECKSUM" : "3U8E5S893S8C3S89",
    "DATASUM" : "0"
  },
  "TS_C_20230523_000295_R22_S11.fits" : { }
}