{
  "__CONTENT__" : "metadata",
  "__COMMON__" : {
    "SIMPLE" : true,
    "BITPIX" : 8,
    "NAXIS" : 0,
    "EXTEND" : true,
    "DATE" : "2023-11-21T01:27:15.802",
    "MJD" : 60269.060599560384,
    "RUNNUM" : "7259D",
    "CCD_MANU" : "ITL",
    "CCD_TYPE" : "3800C",
    "TESTTYPE" : "FLAT",
    "IMGTYPE" : "FLAT",
    "DETSIZE" : "[1:4072,1:4000]",
    "EXPTIME" : 5.0807,
    "FILENAME" : "TS_C_20231120_000133_R22_S11.fits",
    "BINX" : 1,
    "BINY" : 1,
    "CCDGAIN" : 1.0,
    "CCDNOISE" : 10.0,
    "HIERARCH SIMULATED DATE-OBS" : "2023-11-21T01:27:10.596",
    "HIERARCH SIMULATED MJD-OBS" : 60269.060539305676,
    "DATE-TRG" : "2023-11-21T01:27:15.787",
    "MJD-TRG" : 60269.06059938669,
    "IMAGETAG" : "b0149a8fb25df602",
    "CCDSLOT" : "S11",
    "RAFTBAY" : "R22",
    "FIRMWARE" : "3139500e",
    "PLATFORM" : "ir2-teststand",
    "CONTNUM" : "18ed9a7b",
    "DAQVERS" : "R5-V6.8 2023-07-28T01:07:30Z (5480a7e2)",
    "DAQPART" : "ts8",
    "DAQFOLD" : "raw",
    "OBSANNOT" : "",
    "OBSID" : "TS_C_20231120_000133",
    "CAMCODE" : "TS",
    "CONTRLLR" : "C",
    "DAYOBS" : "20231120",
    "SEQNUM" : 133,
    "HEADVER" : 2,
    "INSTRUME" : "LSST-TS8",
    "TELESCOP" : "LSST",
    "TSTAND" : "TS8",
    "SEQFILE" : "FP_ITL_2s_ir2_v26.seq",
    "SEQCKSUM" : "1606982964",
    "LSST_NUM" : "ITL-3800C-062",
    "CCD_SERN" : "20804",
    "REBNAME" : "LCA-13574-093",
    "RAFTNAME" : "LCA-11021_RTM-004",
    "DARKTIME" : 5.19061,
    "TSEQNUM" : 124,
    "FPVERS" : "1.2.4",
    "IHVERS" : "1.1.5-SNAPSHOT",
    "DATE-BEG" : "2023-11-21T01:27:10.596",
    "MJD-BEG" : 60269.060539305676,
    "HIERARCH SIMULATED DATE-END" : "2023-11-21T01:27:15.786",
    "MJD-END" : 60269.06059937505,
    "TIMESYS" : "TAI",
    "FILTER" : "SDSSi",
    "FILTER1" : null,
    "TEMPLED1" : null,
    "TEMPLED2" : null,
    "TEMPBRD" : null,
    "CCOBLED" : null,
    "CCOBCURR" : null,
    "CCOBADC" : null,
    "CCOBFLST" : null,
    "PROJTIME" : null,
    "CCOBFLUX" : null,
    "DATEPBEG" : null,
    "MJDPBEG" : null,
    "DATEPEND" : null,
    "MJDPEND" : null,
    "CHECKSUM" : "4mhn4mfn4mfn4mfn",
    "DATASUM" : "0"
  },
  "TS_C_20231120_000133_R22_S11.fits" : { }
}